whentowork/__init__.py
whentowork/adapter.py
whentowork/client.py
whentowork/models.py
whentowork/exceptions/w2w_bad_request.py
whentowork/exceptions/w2w_bad_type.py
whentowork/types/__init__.py
whentowork/types/category.py
whentowork/types/employee.py
whentowork/types/position.py
whentowork/types/shift.py
whentowork/types/timeoff.py
whentowork-0.0.7.dist-info/LICENSE
whentowork-0.0.7.dist-info/METADATA
whentowork-0.0.7.dist-info/WHEEL
whentowork-0.0.7.dist-info/top_level.txt
whentowork-0.0.7.dist-info/RECORD
