Metadata-Version: 2.1
Name: whentowork
Version: 0.0.7
Summary: A wrapper for the WhenToWork API
Author-email: Patrick Brady <patrick16brady@gmail.com>
License: Copyright (c) 2023-present pfbrady
Project-URL: Homepage, https://github.com/pfbrady/whentowork
Project-URL: Issues, https://github.com/pfbrady/whentowork/issues
Classifier: Programming Language :: Python :: 3
Classifier: License :: OSI Approved :: MIT License
Classifier: Operating System :: OS Independent
Requires-Python: >=3.8
License-File: LICENSE
